{
  "kind": "collectionType",
  "collectionName": "title_descrition_cards",
  "info": {
    "singularName": "title-descrition-card",
    "pluralName": "title-descrition-cards",
    "displayName": "TitleDescritionCards",
    "description": ""
  },
  "options": {
    "draftAndPublish": true
  },
  "pluginOptions": {
    "i18n": {
      "localized": true
    }
  },
  "attributes": {
    "TypeId": {
      "type": "enumeration",
      "enum": [
        "mansory"
      ],
      "pluginOptions": {
        "i18n": {
          "localized": false
        }
      }
    },
    "Title": {
      "type": "string",
      "pluginOptions": {
        "i18n": {
          "localized": true
        }
      }
    },
    "Description": {
      "type": "blocks",
      "pluginOptions": {
        "i18n": {
          "localized": true
        }
      }
    },
    "Cards": {
      "type": "component",
      "repeatable": true,
      "component": "shared.card",
      "pluginOptions": {
        "i18n": {
          "localized": true
        }
      }
    }
  }
}
